charmed_service_mesh_helpers/__init__.py
charmed_service_mesh_helpers/enums.py
charmed_service_mesh_helpers/labels.py
charmed_service_mesh_helpers/models.py
charmed_service_mesh_helpers/interfaces/__init__.py
charmed_service_mesh_helpers/interfaces/gateway_metadata/__init__.py
charmed_service_mesh_helpers/interfaces/gateway_metadata/_gateway_metadata.py
charmed_service_mesh_helpers-0.4.0.dist-info/licenses/LICENSE
charmed_service_mesh_helpers-0.4.0.dist-info/METADATA
charmed_service_mesh_helpers-0.4.0.dist-info/WHEEL
charmed_service_mesh_helpers-0.4.0.dist-info/top_level.txt
charmed_service_mesh_helpers-0.4.0.dist-info/RECORD
