Metadata-Version: 2.4
Name: charmed-service-mesh-helpers
Version: 0.4.0
Summary: Helpers for the Service Mesh charms.
License:                                  Apache License
Classifier: Programming Language :: Python :: 3
Classifier: Operating System :: OS Independent
Requires-Python: ~=3.8
License-File: LICENSE
Requires-Dist: ops~=2.5
Requires-Dist: pydantic>=2
Provides-Extra: dev
Requires-Dist: codespell; extra == "dev"
Requires-Dist: coverage[toml]; extra == "dev"
Requires-Dist: pyright; extra == "dev"
Requires-Dist: pytest; extra == "dev"
Requires-Dist: ruff; extra == "dev"
Dynamic: license-file
